CrawlersTools/__init__.py
CrawlersTools/extractors/__init__.py
CrawlersTools/extractors/attachment_extractor.py
CrawlersTools/extractors/base.py
CrawlersTools/extractors/content_extractor.py
CrawlersTools/extractors/list_extractor.py
CrawlersTools/extractors/time_extractor.py
CrawlersTools/extractors/title_extractor.py
CrawlersTools/extractors/schemas/__init__.py
CrawlersTools/extractors/schemas/element.py
CrawlersTools/extractors/utils/__init__.py
CrawlersTools/extractors/utils/cluster.py
CrawlersTools/extractors/utils/element.py
CrawlersTools/extractors/utils/preprocess.py
CrawlersTools/extractors/utils/settings.py
CrawlersTools/extractors/utils/similarity.py
CrawlersTools/js_crawler/__init__.py
CrawlersTools/js_crawler/font_decrypt.py
CrawlersTools/js_crawler/transfer_js.py
CrawlersTools/logs/__init__.py
CrawlersTools/logs/formatters.py
CrawlersTools/logs/handlers.py
CrawlersTools/logs/log.py
CrawlersTools/logs/logger.py
CrawlersTools/pipelines/__init__.py
CrawlersTools/pipelines/kafka_operate.py
CrawlersTools/pipelines/mongo_pipeline.py
CrawlersTools/pipelines/mysql_pipeline.py
CrawlersTools/pipelines/redis_pipeline.py
CrawlersTools/preprocess/__init__.py
CrawlersTools/preprocess/bloom_filter.py
CrawlersTools/preprocess/time_process.py
CrawlersTools/projects/__init__.py
CrawlersTools/projects/filters.py
CrawlersTools/projects/upload_oss.py
CrawlersTools/requests/__init__.py
CrawlersTools/requests/base_requests.py
CrawlersTools/requests/proxy.py
CrawlersTools/requests/random_ua.py
CrawlersTools/schedules/__init__.py
CrawlersTools/schedules/auto_thread.py
CrawlersTools-1.4.81.dist-info/LICENSE
CrawlersTools-1.4.81.dist-info/METADATA
CrawlersTools-1.4.81.dist-info/WHEEL
CrawlersTools-1.4.81.dist-info/top_level.txt
CrawlersTools-1.4.81.dist-info/RECORD
