Metadata-Version: 2.1
Name: CrawlersTools
Version: 1.4.81
Summary: Tools for Crawlers
Home-page: https://github.com/MuggleK/CrawlersTools
Author: MuggleK
Author-email: peichangchuan@gmail.com
License: BSD License
Platform: all
Classifier: Intended Audience :: Developers
Classifier: Operating System :: OS Independent
Classifier: Natural Language :: Chinese (Simplified)
Classifier: Programming Language :: Python :: 3.7
Classifier: Topic :: Software Development :: Libraries
License-File: LICENSE
Requires-Dist: auto-mix-prep
Requires-Dist: DBUtils ==1.3
Requires-Dist: fontTools
Requires-Dist: httpx
Requires-Dist: httpx[http2]
Requires-Dist: loguru
Requires-Dist: Pillow
Requires-Dist: PyExecJS ==1.5.1
Requires-Dist: pymongo
Requires-Dist: PyMySQL
Requires-Dist: redis
Requires-Dist: tqdm
Requires-Dist: PyYAML
Requires-Dist: lxml
Requires-Dist: numpy
Requires-Dist: Distance
Requires-Dist: chardet
Requires-Dist: sinan
Requires-Dist: kafka-python
